nicknamer/__init__.py
nicknamer/nicknamer_alphanumeric.py
nicknamer/nicknamer_base.py
nicknamer/nicknamer_words.py
nicknamer/py.typed
nicknamer/resources/adjective.txt
nicknamer/resources/noun.txt
nicknamer/resources/verb.txt
nicknamer-0.0.3.dist-info/licenses/LICENSE
nicknamer-0.0.3.dist-info/METADATA
nicknamer-0.0.3.dist-info/WHEEL
nicknamer-0.0.3.dist-info/top_level.txt
nicknamer-0.0.3.dist-info/RECORD
