Metadata-Version: 2.4
Name: nicknamer
Version: 0.0.3
Summary: A random name generator
Author-email: "Mobius Logic, Inc." <145808634+dm-ackerman@users.noreply.github.com>
License-Expression: Apache-2.0
Project-URL: Homepage, https://github.com/mobius-logic/nicknamer
Project-URL: Issues, https://github.com/mobius-logic/nicknamer/issues
Classifier: Programming Language :: Python :: 3
Classifier: Operating System :: OS Independent
Requires-Python: >=3.10
License-File: LICENSE
Requires-Dist: typing_extensions
Provides-Extra: dev
Requires-Dist: pre-commit; extra == "dev"
Requires-Dist: pytest; extra == "dev"
Dynamic: license-file
